[
    {
        "title": "News",
        "pid": 0,
        "id": 1
    },
    {
        "title": "\u4e66",
        "pid": 0,
        "id": 6
    },
    {
        "title": "Attachments",
        "pid": 0,
        "id": 11
    },
    {
        "title": "\u5546\u54c1",
        "pid": 0,
        "id": 4
    },
    {
        "title": "\u8bba\u575b",
        "pid": 0,
        "id": 2
    },
    {
        "title": "\u535a\u5ba2",
        "pid": 0,
        "id": 3
    },
    {
        "title": "\u5e7b\u706f\u7247",
        "pid": 0,
        "id": 5
    },
    {
        "title": "Navigation",
        "pid": 0,
        "id": 13
    },
    {
        "title": "Code Template",
        "pid": 0,
        "id": 52
    },
    {
        "title": "BaoAI \u65b0\u95fb",
        "pid": 1,
        "id": 85
    },
    {
        "title": "AI",
        "pid": 1,
        "id": 18
    },
    {
        "title": "\u91cf\u5316",
        "pid": 1,
        "id": 19
    },
    {
        "title": "Index Slide",
        "pid": 5,
        "id": 20
    },
    {
        "title": "\u7cfb\u7edf\u6a21\u5757",
        "pid": 6,
        "id": 88
    },
    {
        "title": "BaoAI",
        "pid": 6,
        "id": 50
    },
    {
        "title": "BaoAI Front",
        "pid": 6,
        "id": 46
    },
    {
        "title": "BaoAI Backend",
        "pid": 6,
        "id": 48
    },
    {
        "title": "BaoAI \u91d1\u878d\u6570\u636e\u91c7\u96c6\u7cfb\u7edf",
        "pid": 6,
        "id": 12
    },
    {
        "title": "BaoAI \u91cf\u5316\u7cfb\u7edf\uff1aCerebro\u5927\u8111",
        "pid": 6,
        "id": 73
    },
    {
        "title": "BaoAI \u91cf\u5316\u7cfb\u7edf\uff1a\u7ecf\u7eaa\u4eba",
        "pid": 6,
        "id": 72
    },
    {
        "title": "BaoAI\u91cf\u5316\u7cfb\u7edf\uff1a\u6307\u6807",
        "pid": 6,
        "id": 66
    },
    {
        "title": "BaoAI\u91cf\u5316\u7cfb\u7edf\uff1a\u9009\u62e9\u7b56\u7565",
        "pid": 6,
        "id": 68
    },
    {
        "title": "BaoAI\u91cf\u5316\u7cfb\u7edf\uff1a\u4ea4\u6613\u7b56\u7565",
        "pid": 6,
        "id": 78
    },
    {
        "title": "BaoAI\u91cf\u5316\u7cfb\u7edf\uff1a\u8ba2\u5355",
        "pid": 6,
        "id": 74
    },
    {
        "title": "BaoAI \u91cf\u5316\u7cfb\u7edf\uff1aPyfolio",
        "pid": 6,
        "id": 75
    },
    {
        "title": "Pandas",
        "pid": 6,
        "id": 28
    },
    {
        "title": "Tushare",
        "pid": 6,
        "id": 62
    },
    {
        "title": "Python",
        "pid": 6,
        "id": 44
    },
    {
        "title": "BaoAI \u65b0\u95fb",
        "pid": 6,
        "id": 83
    },
    {
        "title": "BaoAI \u65b0\u95fb",
        "pid": 6,
        "id": 84
    },
    {
        "title": "talib \u4e2d\u6587\u6587\u6863",
        "pid": 6,
        "id": 58
    },
    {
        "title": "\u4ece\u96f6\u6784\u5efa\u91cf\u5316\u7cfb\u7edf",
        "pid": 6,
        "id": 61
    },
    {
        "title": "\u4eba\u5de5\u667a\u80fd",
        "pid": 6,
        "id": 63
    },
    {
        "title": "Backtrader",
        "pid": 6,
        "id": 55
    },
    {
        "title": "Person",
        "pid": 8,
        "id": 9
    },
    {
        "title": "Nature",
        "pid": 8,
        "id": 10
    },
    {
        "title": "Image",
        "pid": 11,
        "id": 8
    },
    {
        "title": "Stock Data",
        "pid": 11,
        "id": 51
    },
    {
        "title": "\u5185\u5bb9",
        "pid": 13,
        "id": 14
    },
    {
        "title": "\u624b\u518c",
        "pid": 13,
        "id": 33
    },
    {
        "title": "\u91cf\u5316\u7cfb\u7edf",
        "pid": 13,
        "id": 39
    },
    {
        "title": "BaoAI \u65b0\u95fb",
        "pid": 14,
        "id": 15
    },
    {
        "title": "divider1",
        "pid": 14,
        "id": 41
    },
    {
        "title": "\u5173\u4e8e\u6211\u4eec",
        "pid": 14,
        "id": 40
    },
    {
        "title": "first",
        "pid": 20,
        "id": 21
    },
    {
        "title": "second slide",
        "pid": 20,
        "id": 22
    },
    {
        "title": "\u4f7f\u7528",
        "pid": 28,
        "id": 29
    },
    {
        "title": "Python\u4f7f\u7528",
        "pid": 44,
        "id": 45
    },
    {
        "title": "\u5f00\u53d1\u73af\u5883\u642d\u5efa",
        "pid": 46,
        "id": 86
    },
    {
        "title": "\u624b\u518cBook",
        "pid": 46,
        "id": 47
    },
    {
        "title": "\u9879\u76ee\u5f00\u53d1",
        "pid": 46,
        "id": 87
    },
    {
        "title": "\u5f00\u53d1\u73af\u5883\u5efa\u7acb",
        "pid": 48,
        "id": 49
    },
    {
        "title": "BaoAIBack\u5e38\u7528Python\u5e93",
        "pid": 48,
        "id": 54
    },
    {
        "title": "\u914d\u7f6e",
        "pid": 48,
        "id": 97
    },
    {
        "title": "\u5b89\u88c5\u90e8\u7f72",
        "pid": 50,
        "id": 79
    },
    {
        "title": "Nginx",
        "pid": 50,
        "id": 80
    },
    {
        "title": "AnguarJS",
        "pid": 50,
        "id": 81
    },
    {
        "title": "Task Template",
        "pid": 52,
        "id": 53
    },
    {
        "title": "\u57fa\u7840",
        "pid": 55,
        "id": 56
    },
    {
        "title": "\u63d0\u9ad8",
        "pid": 55,
        "id": 57
    },
    {
        "title": "\u5165\u95e8",
        "pid": 58,
        "id": 59
    },
    {
        "title": "\u652f\u6301\u7684\u6307\u6807",
        "pid": 58,
        "id": 60
    },
    {
        "title": "\u91cf\u5316\u57fa\u7840\u6982\u5ff5",
        "pid": 61,
        "id": 65
    },
    {
        "title": "\u6982\u7387\u8bba",
        "pid": 63,
        "id": 64
    },
    {
        "title": "\u5f62\u6001\u8bc6\u522b",
        "pid": 66,
        "id": 67
    },
    {
        "title": "\u91cd\u53e0\u6307\u6807",
        "pid": 66,
        "id": 69
    },
    {
        "title": "\u901a\u7528",
        "pid": 68,
        "id": 77
    },
    {
        "title": "\u5f62\u6001\u8bc6\u522b",
        "pid": 68,
        "id": 70
    },
    {
        "title": "\u91cd\u53e0\u4ea4\u6613\u7b56\u7565",
        "pid": 78,
        "id": 71
    },
    {
        "title": "\u6d4b\u8bd5\u7b56\u7565",
        "pid": 78,
        "id": 76
    },
    {
        "title": "BaoAI \u6838\u5fc3\u5e73\u53f0",
        "pid": 88,
        "id": 89
    },
    {
        "title": "\u81ea\u52a8\u4ee3\u7801",
        "pid": 88,
        "id": 90
    },
    {
        "title": "\u4efb\u52a1\u7cfb\u7edf",
        "pid": 88,
        "id": 91
    },
    {
        "title": "\u5185\u5bb9\u7ba1\u7406",
        "pid": 88,
        "id": 92
    },
    {
        "title": "\u4eba\u5de5\u667a\u80fd",
        "pid": 88,
        "id": 93
    },
    {
        "title": "\u91d1\u878d\u6570\u636e\u91c7\u96c6",
        "pid": 88,
        "id": 94
    },
    {
        "title": "\u5927\u6570\u636e",
        "pid": 88,
        "id": 95
    },
    {
        "title": "\u91cf\u5316",
        "pid": 88,
        "id": 96
    }
]
